features/__init__.py
features/feature_generation.py
features/feature_spec.py
features/hyper_feature.py
features/sql_gen.py
features/templates/fact_aggregations.j2
features/templates/timeseries_growth.j2
features/templates/timeseries_growth_m.j2
features/templates/type1_lookup.j2
features/templates/type2_lookup.j2
feature_store_utils-0.0.5.dist-info/LICENSE
feature_store_utils-0.0.5.dist-info/METADATA
feature_store_utils-0.0.5.dist-info/WHEEL
feature_store_utils-0.0.5.dist-info/top_level.txt
feature_store_utils-0.0.5.dist-info/RECORD
