Metadata-Version: 2.1
Name: feature_store_utils
Version: 0.0.5
Summary: A utility to generate ML features from yaml
Author-email: Example Author <author@example.com>
Classifier: Programming Language :: Python :: 3
Classifier: License :: OSI Approved :: MIT License
Classifier: Operating System :: OS Independent
Requires-Python: >=3.7
License-File: LICENSE
Requires-Dist: python-dotenv
Requires-Dist: databricks.feature_engineering
Requires-Dist: Jinja2
Requires-Dist: pandas
Requires-Dist: pyaml
